titlecase/__init__.py
titlecase/tests.py
titlecase-1.1.1.dist-info/LICENSE.md
titlecase-1.1.1.dist-info/METADATA
titlecase-1.1.1.dist-info/WHEEL
titlecase-1.1.1.dist-info/entry_points.txt
titlecase-1.1.1.dist-info/top_level.txt
titlecase-1.1.1.dist-info/RECORD
