Metadata-Version: 1.1
Name: titlecase
Version: 1.1.1
Summary: Python Port of John Gruber's titlecase.pl
Home-page: https://github.com/ppannuto/python-titlecase
Author: Pat Pannuto, Stuart Colville, John Gruber
Author-email: pat.pannuto+titlecase@gmail.com
License: MIT
Keywords: string formatting
Platform: UNKNOWN
Classifier: Development Status :: 5 - Production/Stable
Classifier: Intended Audience :: Developers
Classifier: Operating System :: OS Independent
Classifier: Programming Language :: Python
Classifier: Programming Language :: Python :: 3
Classifier: Programming Language :: Python :: 3.4
Classifier: Programming Language :: Python :: 3.5
Classifier: Programming Language :: Python :: 3.6
Classifier: Programming Language :: Python :: 3.7
Classifier: Programming Language :: Python :: 3.8
Classifier: Programming Language :: Python :: Implementation :: CPython
Classifier: License :: OSI Approved :: MIT License
Classifier: Natural Language :: English
Classifier: Topic :: Text Processing :: Filters
